pyesxi/__init__.py
pyesxi/dellemc.py
pyesxi/dellemc_get_system_inventory.py
pyesxi-0.0.3.dist-info/METADATA
pyesxi-0.0.3.dist-info/WHEEL
pyesxi-0.0.3.dist-info/top_level.txt
pyesxi-0.0.3.dist-info/RECORD
