Metadata-Version: 2.1
Name: pyesxi
Version: 0.0.3
Summary: DELL ESXI SDK package
Home-page: https://github.com/Maliaotw/pyesxi.git
Author: Maliao
Author-email: maliaotw@gmail.com
License: UNKNOWN
Platform: UNKNOWN
Classifier: Programming Language :: Python :: 3
Classifier: License :: OSI Approved :: MIT License
Classifier: Operating System :: OS Independent
Requires-Python: >=3.6
Requires-Dist: ansible (==2.9.2)
Requires-Dist: pysnmp (>=4.4.1)
Requires-Dist: requests (>=2.12.3)
Requires-Dist: PyYAML (>=3.12)
Requires-Dist: future (>=0.16.0)
Requires-Dist: pysnmp-mibs (>=0)
